codesecdirectmpl2/__init__.py
codesecdirectmpl2/module1.py
codesecdirectmpl2-0.2.0.dist-info/LICENSE
codesecdirectmpl2-0.2.0.dist-info/METADATA
codesecdirectmpl2-0.2.0.dist-info/WHEEL
codesecdirectmpl2-0.2.0.dist-info/top_level.txt
codesecdirectmpl2-0.2.0.dist-info/RECORD
